icepandas/__init__.py
icepandas/icepandas.py
icepandas-0.0.5.dist-info/LICENSE
icepandas-0.0.5.dist-info/METADATA
icepandas-0.0.5.dist-info/WHEEL
icepandas-0.0.5.dist-info/top_level.txt
icepandas-0.0.5.dist-info/RECORD
